{
  "geometry": {
    "type": "Polygon", 
    "coordinates": []
  }, 
  "type": "FeatureCollection", 
  "features": [
    {
      "id": 35310293, 
      "properties": {
        "oep-star:magV": null, 
        "oep:new": [
          "0", 
          "0"
        ], 
        "oep:id_exoplaneteu": "Kepler-38(AB) b", 
        "oep-star:rightascension": "19 07 19", 
        "oep-star:magK": null, 
        "placetype": "planet", 
        "oep:imagedescription": [
          null, 
          null
        ], 
        "oep-star:declination": "+42 16 45", 
        "oep-star:spectraltype": null, 
        "oep-star:magJ": null, 
        "oep-star:magI": null, 
        "oep:lastupdate": "12/08/24", 
        "oep:image": [
          null, 
          null
        ], 
        "oep:discoveryyear": "2012", 
        "oep-orbit:inclination": "90.182", 
        "oep-star:radius": null, 
        "oep:description": [
          "Kepler-38(AB) b is a Neptune-sized planet orbiting a binary star (therefore the name with AB). The stellar mass quoted here is the sum of the two stellar components. The planet is not sufficiently massive to alter the orbit of the binary. Therefore one can only place an upper limit on the mass of the planet of 122 Earth masses.", 
          null
        ], 
        "oep:multiplicity": "1", 
        "artisanal:id": 35310293, 
        "woe:id": 35310293, 
        "oep-star:magH": null, 
        "oep-star:distance": null, 
        "oep:list": "Confirmed planets", 
        "oep:discoverymethod": "transit", 
        "oep:mass": null, 
        "oep:id": "Kepler-38(AB) b", 
        "oep:radius": "0.39641678", 
        "oep-orbit:period": "105.595", 
        "oep-orbit:eccentricity": "0.032", 
        "oep-star:mass": "1.18", 
        "oep-orbit:semimajoraxis": "0.4644", 
        "artisanal:foundry": "http://www.brooklynintegers.com/", 
        "oep-star:angulardistance": null, 
        "oep-star:metallicity": null, 
        "oep:name": [
          "Kepler-38(AB) b", 
          "KIC 6762829", 
          "KOI-1740", 
          "2MASS J19071928+4216451", 
          "Kepler-38 b"
        ]
      }
    }
  ]
}